{
  "annotations": {
    "list": [
      {
        "builtIn": 1,
        "datasource": {
          "type": "grafana",
          "uid": "-- Grafana --"
        },
        "enable": true,
        "hide": true,
        "iconColor": "rgba(0, 211, 255, 1)",
        "name": "Annotations & Alerts",
        "type": "dashboard"
      }
    ]
  },
  "editable": true,
  "fiscalYearStartMonth": 0,
  "graphTooltip": 0,
  "id": 5,
  "links": [],
  "panels": [
    {
      "datasource": {
        "type": "postgres",
        "uid": "PA07283B22CEA3051"
      },
      "fieldConfig": {
        "defaults": {
          "color": {
            "mode": "thresholds"
          },
          "mappings": [],
          "thresholds": {
            "mode": "absolute",
            "steps": [
              {
                "color": "green",
                "value": null
              }
            ]
          },
          "unit": "currencyUSD"
        },
        "overrides": []
      },
      "gridPos": {
        "h": 8,
        "w": 8,
        "x": 0,
        "y": 0
      },
      "id": 1,
      "options": {
        "colorMode": "value",
        "graphMode": "area",
        "justifyMode": "auto",
        "orientation": "auto",
        "percentChangeColorMode": "standard",
        "reduceOptions": {
          "calcs": [
            "sum"
          ],
          "fields": "",
          "values": false
        },
        "showPercentChange": false,
        "textMode": "auto",
        "wideLayout": true
      },
      "pluginVersion": "11.4.0",
      "targets": [
        {
          "datasource": {
            "type": "postgres",
            "uid": "PA07283B22CEA3051"
          },
          "editorMode": "code",
          "format": "table",
          "rawQuery": true,
          "rawSql": "SELECT SUM(amount) as \"Total Spent\" FROM transactions WHERE amount > 0;",
          "refId": "A",
          "sql": {
            "columns": [
              {
                "parameters": [],
                "type": "function"
              }
            ],
            "groupBy": [
              {
                "property": {
                  "type": "string"
                },
                "type": "groupBy"
              }
            ],
            "limit": 50
          }
        }
      ],
      "title": "Total Spending",
      "type": "stat"
    },
    {
      "datasource": {
        "type": "postgres",
        "uid": "PA07283B22CEA3051"
      },
      "fieldConfig": {
        "defaults": {
          "color": {
            "mode": "thresholds"
          },
          "mappings": [],
          "thresholds": {
            "mode": "absolute",
            "steps": [
              {
                "color": "green",
                "value": null
              }
            ]
          },
          "unit": "currencyUSD"
        },
        "overrides": []
      },
      "gridPos": {
        "h": 8,
        "w": 8,
        "x": 8,
        "y": 0
      },
      "id": 2,
      "options": {
        "colorMode": "value",
        "graphMode": "area",
        "justifyMode": "auto",
        "orientation": "auto",
        "percentChangeColorMode": "standard",
        "reduceOptions": {
          "calcs": [
            "sum"
          ],
          "fields": "",
          "values": false
        },
        "showPercentChange": false,
        "textMode": "auto",
        "wideLayout": true
      },
      "pluginVersion": "11.4.0",
      "targets": [
        {
          "datasource": {
            "type": "postgres",
            "uid": "PA07283B22CEA3051"
          },
          "editorMode": "code",
          "format": "table",
          "rawQuery": true,
          "rawSql": "SELECT ABS(SUM(amount)) as \"Total Payments\" FROM transactions WHERE amount < 0;",
          "refId": "A"
        }
      ],
      "title": "Total Payments",
      "type": "stat"
    },
    {
      "datasource": {
        "type": "postgres",
        "uid": "PA07283B22CEA3051"
      },
      "fieldConfig": {
        "defaults": {
          "color": {
            "mode": "thresholds"
          },
          "mappings": [],
          "thresholds": {
            "mode": "absolute",
            "steps": [
              {
                "color": "green",
                "value": null
              }
            ]
          }
        },
        "overrides": []
      },
      "gridPos": {
        "h": 8,
        "w": 8,
        "x": 16,
        "y": 0
      },
      "id": 3,
      "options": {
        "colorMode": "value",
        "graphMode": "area",
        "justifyMode": "auto",
        "orientation": "auto",
        "percentChangeColorMode": "standard",
        "reduceOptions": {
          "calcs": [
            "lastNotNull"
          ],
          "fields": "",
          "values": false
        },
        "showPercentChange": false,
        "textMode": "auto",
        "wideLayout": true
      },
      "pluginVersion": "11.4.0",
      "targets": [
        {
          "datasource": {
            "type": "postgres",
            "uid": "PA07283B22CEA3051"
          },
          "editorMode": "code",
          "format": "table",
          "rawQuery": true,
          "rawSql": "SELECT COUNT(*) as \"Transaction Count\" FROM transactions;",
          "refId": "A"
        }
      ],
      "title": "Transaction Count",
      "type": "stat"
    },
    {
      "datasource": {
        "type": "postgres",
        "uid": "PA07283B22CEA3051"
      },
      "fieldConfig": {
        "defaults": {
          "custom": {
            "align": "auto",
            "cellOptions": {
              "type": "auto"
            },
            "inspect": false
          },
          "mappings": [],
          "thresholds": {
            "mode": "absolute",
            "steps": [
              {
                "color": "green",
                "value": null
              }
            ]
          }
        },
        "overrides": [
          {
            "matcher": {
              "id": "byName",
              "options": "amount"
            },
            "properties": [
              {
                "id": "unit",
                "value": "currencyUSD"
              }
            ]
          }
        ]
      },
      "gridPos": {
        "h": 10,
        "w": 24,
        "x": 0,
        "y": 8
      },
      "id": 4,
      "options": {
        "cellHeight": "sm",
        "footer": {
          "countRows": false,
          "fields": "",
          "reducer": [
            "sum"
          ],
          "show": false
        },
        "showHeader": true,
        "sortBy": [
          {
            "desc": true,
            "displayName": "amount"
          }
        ]
      },
      "pluginVersion": "11.4.0",
      "targets": [
        {
          "datasource": {
            "type": "postgres",
            "uid": "PA07283B22CEA3051"
          },
          "editorMode": "code",
          "format": "table",
          "rawQuery": true,
          "rawSql": "SELECT \n  t.transaction_date,\n  a.bank_name,\n  a.card_name,\n  t.description,\n  t.amount,\n  t.transaction_type\nFROM transactions t\nJOIN accounts a ON t.account_id = a.id\nWHERE t.transaction_type = 'credit'\nORDER BY t.transaction_date DESC\nLIMIT 500;",
          "refId": "A",
          "sql": {
            "columns": [
              {
                "parameters": [],
                "type": "function"
              }
            ],
            "groupBy": [
              {
                "property": {
                  "type": "string"
                },
                "type": "groupBy"
              }
            ],
            "limit": 50
          }
        }
      ],
      "title": "Recent Transactions",
      "type": "table"
    },
    {
      "datasource": {
        "type": "postgres",
        "uid": "PA07283B22CEA3051"
      },
      "fieldConfig": {
        "defaults": {
          "color": {
            "mode": "palette-classic"
          },
          "custom": {
            "axisBorderShow": false,
            "axisCenteredZero": false,
            "axisColorMode": "text",
            "axisLabel": "",
            "axisPlacement": "auto",
            "barAlignment": 0,
            "barWidthFactor": 0.6,
            "drawStyle": "bars",
            "fillOpacity": 80,
            "gradientMode": "none",
            "hideFrom": {
              "legend": false,
              "tooltip": false,
              "viz": false
            },
            "insertNulls": false,
            "lineInterpolation": "linear",
            "lineWidth": 1,
            "pointSize": 5,
            "scaleDistribution": {
              "type": "linear"
            },
            "showPoints": "auto",
            "spanNulls": false,
            "stacking": {
              "group": "A",
              "mode": "none"
            },
            "thresholdsStyle": {
              "mode": "off"
            }
          },
          "mappings": [],
          "thresholds": {
            "mode": "absolute",
            "steps": [
              {
                "color": "green",
                "value": null
              }
            ]
          },
          "unit": "currencyUSD"
        },
        "overrides": []
      },
      "gridPos": {
        "h": 9,
        "w": 24,
        "x": 0,
        "y": 18
      },
      "id": 5,
      "options": {
        "legend": {
          "calcs": [],
          "displayMode": "list",
          "placement": "bottom",
          "showLegend": true
        },
        "tooltip": {
          "mode": "single",
          "sort": "none"
        }
      },
      "pluginVersion": "11.4.0",
      "targets": [
        {
          "datasource": {
            "type": "postgres",
            "uid": "PA07283B22CEA3051"
          },
          "editorMode": "code",
          "format": "table",
          "rawQuery": true,
          "rawSql": "SELECT \n  transaction_date as time,\n  SUM(amount) as \"Spending\"\nFROM transactions\nWHERE transaction_type = 'credit'\nGROUP BY transaction_date\nORDER BY transaction_date;",
          "refId": "A"
        }
      ],
      "title": "Daily Spending",
      "type": "timeseries"
    }
  ],
  "preload": false,
  "refresh": "",
  "schemaVersion": 40,
  "tags": [
    "finance"
  ],
  "templating": {
    "list": []
  },
  "time": {
    "from": "2024-01-01T08:00:00.000Z",
    "to": "2025-01-01T07:59:59.000Z"
  },
  "timepicker": {},
  "timezone": "browser",
  "title": "Finance Dashboard",
  "uid": "finance-overview",
  "version": 5,
  "weekStart": ""
}